segment_anything/__init__.py
segment_anything/automatic_mask_generator.py
segment_anything/build_sam.py
segment_anything/predictor.py
segment_anything/modeling/__init__.py
segment_anything/modeling/common.py
segment_anything/modeling/image_encoder.py
segment_anything/modeling/mask_decoder.py
segment_anything/modeling/prompt_encoder.py
segment_anything/modeling/sam.py
segment_anything/modeling/transformer.py
segment_anything/utils/__init__.py
segment_anything/utils/amg.py
segment_anything/utils/onnx.py
segment_anything/utils/transforms.py
segment_anything_iscas-1.1.dist-info/LICENSE
segment_anything_iscas-1.1.dist-info/METADATA
segment_anything_iscas-1.1.dist-info/WHEEL
segment_anything_iscas-1.1.dist-info/top_level.txt
segment_anything_iscas-1.1.dist-info/RECORD
